{
  "_note": "Enrichment queue: notable theories NOT already in theories.seed.json. hint_* are starting guesses; enrichment agents correct per rubric. genre keys: government, espionage, alt-history, science-tech, health, extraterrestrial, religion-occult, finance, deaths, ethnic-religious, new-world-order, media-surveillance.",
  "queue": [
    {"name":"Operation Gladio","hint_genre":"government","hint_year":1990,"hint_status":"confirmed"},
    {"name":"Pentagon Papers","hint_genre":"government","hint_year":1971,"hint_status":"confirmed"},
    {"name":"Bay of Pigs Invasion","hint_genre":"government","hint_year":1961,"hint_status":"confirmed"},
    {"name":"Operation Paperclip","hint_genre":"government","hint_year":1946,"hint_status":"confirmed"},
    {"name":"Operation Midnight Climax","hint_genre":"government","hint_year":1960,"hint_status":"confirmed"},
    {"name":"Operation Snow White","hint_genre":"religion-occult","hint_year":1977,"hint_status":"confirmed"},
    {"name":"COINTELPRO Black Panther targeting","hint_genre":"espionage","hint_year":1969,"hint_status":"confirmed"},
    {"name":"Church Committee revelations","hint_genre":"government","hint_year":1975,"hint_status":"confirmed"},
    {"name":"Pearl Harbor Advance Knowledge","hint_genre":"government","hint_year":1941,"hint_status":"fringe"},
    {"name":"Waco Siege Cover-up","hint_genre":"government","hint_year":1993,"hint_status":"contested"},
    {"name":"Oklahoma City Bombing Second Bomb","hint_genre":"government","hint_year":1995,"hint_status":"fringe"},
    {"name":"TWA Flight 800 Missile Theory","hint_genre":"government","hint_year":1996,"hint_status":"debunked"},
    {"name":"Jonestown MKUltra Theory","hint_genre":"government","hint_year":1978,"hint_status":"fringe"},
    {"name":"FEMA Camps","hint_genre":"government","hint_year":2009,"hint_status":"debunked"},
    {"name":"Agenda 21","hint_genre":"new-world-order","hint_year":1992,"hint_status":"fringe"},
    {"name":"Project Blue Beam","hint_genre":"new-world-order","hint_year":1994,"hint_status":"fringe"},
    {"name":"Georgia Guidestones","hint_genre":"new-world-order","hint_year":1980,"hint_status":"fringe"},
    {"name":"Denver International Airport","hint_genre":"new-world-order","hint_year":1995,"hint_status":"fringe"},
    {"name":"Skull and Bones","hint_genre":"religion-occult","hint_year":1873,"hint_status":"fringe"},
    {"name":"George Soros Puppet Master","hint_genre":"finance","hint_year":2016,"hint_status":"fringe"},
    {"name":"Cultural Marxism","hint_genre":"new-world-order","hint_year":1998,"hint_status":"fringe"},
    {"name":"The Great Replacement","hint_genre":"ethnic-religious","hint_year":2011,"hint_status":"debunked"},
    {"name":"White Genocide","hint_genre":"ethnic-religious","hint_year":1995,"hint_status":"debunked"},
    {"name":"Eurabia","hint_genre":"ethnic-religious","hint_year":2005,"hint_status":"debunked"},
    {"name":"Love Jihad","hint_genre":"ethnic-religious","hint_year":2009,"hint_status":"debunked"},
    {"name":"Zionist Occupation Government (ZOG)","hint_genre":"ethnic-religious","hint_year":1976,"hint_status":"debunked"},
    {"name":"Holocaust Denial","hint_genre":"ethnic-religious","hint_year":1969,"hint_status":"debunked"},
    {"name":"Blood Libel","hint_genre":"ethnic-religious","hint_year":1144,"hint_status":"debunked"},
    {"name":"Well Poisoning (Black Death)","hint_genre":"ethnic-religious","hint_year":1348,"hint_status":"debunked"},
    {"name":"Jewish Bolshevism","hint_genre":"ethnic-religious","hint_year":1917,"hint_status":"debunked"},
    {"name":"Khazarian Mafia","hint_genre":"ethnic-religious","hint_year":2010,"hint_status":"debunked"},
    {"name":"Barack Obama Birther Theory","hint_genre":"government","hint_year":2008,"hint_status":"debunked"},
    {"name":"Obama Secret Muslim","hint_genre":"government","hint_year":2008,"hint_status":"debunked"},
    {"name":"Clinton Body Count","hint_genre":"deaths","hint_year":1993,"hint_status":"debunked"},
    {"name":"Seth Rich Murder","hint_genre":"deaths","hint_year":2016,"hint_status":"debunked"},
    {"name":"2020 Stolen Election","hint_genre":"government","hint_year":2020,"hint_status":"debunked"},
    {"name":"January 6 False Flag","hint_genre":"government","hint_year":2021,"hint_status":"debunked"},
    {"name":"BlueAnon","hint_genre":"government","hint_year":2020,"hint_status":"fringe"},
    {"name":"Crisis Actors","hint_genre":"government","hint_year":2012,"hint_status":"debunked"},
    {"name":"Predictive Programming","hint_genre":"media-surveillance","hint_year":2002,"hint_status":"fringe"},
    {"name":"Targeted Individuals","hint_genre":"media-surveillance","hint_year":2003,"hint_status":"fringe"},
    {"name":"RFID Chip Implantation","hint_genre":"media-surveillance","hint_year":1998,"hint_status":"fringe"},
    {"name":"Smartphones Listening for Ads","hint_genre":"media-surveillance","hint_year":2016,"hint_status":"contested"},
    {"name":"Dead Internet Theory","hint_genre":"media-surveillance","hint_year":2021,"hint_status":"fringe"},
    {"name":"Bitcoin Government Creation","hint_genre":"finance","hint_year":2011,"hint_status":"fringe"},
    {"name":"Gold Standard Suppression","hint_genre":"finance","hint_year":1971,"hint_status":"fringe"},
    {"name":"Diana Assassination","hint_genre":"deaths","hint_year":1997,"hint_status":"debunked"},
    {"name":"Elvis Faked His Death","hint_genre":"deaths","hint_year":1977,"hint_status":"debunked"},
    {"name":"Hitler Survived / Escaped to Argentina","hint_genre":"alt-history","hint_year":1945,"hint_status":"debunked"},
    {"name":"Tupac Shakur Is Alive","hint_genre":"deaths","hint_year":1996,"hint_status":"debunked"},
    {"name":"Avril Lavigne Replacement","hint_genre":"deaths","hint_year":2011,"hint_status":"debunked"},
    {"name":"Kurt Cobain Was Murdered","hint_genre":"deaths","hint_year":1994,"hint_status":"contested"},
    {"name":"John Lennon Assassination Conspiracy","hint_genre":"deaths","hint_year":1980,"hint_status":"fringe"},
    {"name":"Pope John Paul I Murder","hint_genre":"deaths","hint_year":1978,"hint_status":"contested"},
    {"name":"Olof Palme Assassination","hint_genre":"deaths","hint_year":1986,"hint_status":"contested"},
    {"name":"David Kelly Death","hint_genre":"deaths","hint_year":2003,"hint_status":"contested"},
    {"name":"Zachary Taylor Poisoning","hint_genre":"deaths","hint_year":1850,"hint_status":"debunked"},
    {"name":"Abraham Lincoln Assassination Conspiracy","hint_genre":"deaths","hint_year":1865,"hint_status":"plausible"},
    {"name":"Subhas Chandra Bose Survival","hint_genre":"deaths","hint_year":1945,"hint_status":"contested"},
    {"name":"Malaysia Airlines MH370","hint_genre":"government","hint_year":2014,"hint_status":"debunked"},
    {"name":"Malaysia Airlines MH17 Cover-up","hint_genre":"government","hint_year":2014,"hint_status":"debunked"},
    {"name":"Korean Air Lines Flight 007","hint_genre":"espionage","hint_year":1983,"hint_status":"contested"},
    {"name":"Nibiru / Planet X Cataclysm","hint_genre":"extraterrestrial","hint_year":1995,"hint_status":"debunked"},
    {"name":"Hollow Earth","hint_genre":"alt-history","hint_year":1818,"hint_status":"debunked"},
    {"name":"Black Knight Satellite","hint_genre":"extraterrestrial","hint_year":1954,"hint_status":"fringe"},
    {"name":"Bermuda Triangle","hint_genre":"science-tech","hint_year":1964,"hint_status":"fringe"},
    {"name":"Mars Face at Cydonia","hint_genre":"extraterrestrial","hint_year":1976,"hint_status":"debunked"},
    {"name":"Nazca Lines Alien Runways","hint_genre":"extraterrestrial","hint_year":1968,"hint_status":"fringe"},
    {"name":"Majestic 12","hint_genre":"extraterrestrial","hint_year":1984,"hint_status":"debunked"},
    {"name":"Cattle Mutilation","hint_genre":"extraterrestrial","hint_year":1967,"hint_status":"fringe"},
    {"name":"Rendlesham Forest Incident","hint_genre":"extraterrestrial","hint_year":1980,"hint_status":"contested"},
    {"name":"Anunnaki Ancient Aliens","hint_genre":"extraterrestrial","hint_year":1976,"hint_status":"fringe"},
    {"name":"Secret Space Program","hint_genre":"extraterrestrial","hint_year":1995,"hint_status":"fringe"},
    {"name":"Skinwalker Ranch","hint_genre":"extraterrestrial","hint_year":1996,"hint_status":"fringe"},
    {"name":"Tesla Free Energy Suppression","hint_genre":"science-tech","hint_year":1930,"hint_status":"fringe"},
    {"name":"Technology Suppression (EV1, lightbulb)","hint_genre":"science-tech","hint_year":1924,"hint_status":"contested"},
    {"name":"Philadelphia Experiment","hint_genre":"science-tech","hint_year":1955,"hint_status":"debunked"},
    {"name":"Montauk Project","hint_genre":"science-tech","hint_year":1992,"hint_status":"fringe"},
    {"name":"CERN Black Hole / Portal","hint_genre":"science-tech","hint_year":2008,"hint_status":"fringe"},
    {"name":"Cold Fusion Suppression","hint_genre":"science-tech","hint_year":1989,"hint_status":"debunked"},
    {"name":"GMO Population Control","hint_genre":"health","hint_year":2000,"hint_status":"fringe"},
    {"name":"Aspartame Cancer Cover-up","hint_genre":"health","hint_year":1980,"hint_status":"contested"},
    {"name":"Homeopathy Suppression","hint_genre":"health","hint_year":1980,"hint_status":"debunked"},
    {"name":"Cell Phone / EMF Cancer","hint_genre":"health","hint_year":1993,"hint_status":"contested"},
    {"name":"HIV/AIDS Man-Made Bioweapon","hint_genre":"health","hint_year":1985,"hint_status":"debunked"},
    {"name":"Lyme Disease Plum Island Bioweapon","hint_genre":"health","hint_year":2004,"hint_status":"debunked"},
    {"name":"Gain-of-Function Pandemic Risk","hint_genre":"health","hint_year":2011,"hint_status":"contested"},
    {"name":"AIDS Denialism","hint_genre":"health","hint_year":1987,"hint_status":"debunked"},
    {"name":"Morgellons Disease","hint_genre":"health","hint_year":2002,"hint_status":"contested"},
    {"name":"Bill Gates Population Control","hint_genre":"health","hint_year":2020,"hint_status":"debunked"},
    {"name":"Climate Change Hoax","hint_genre":"science-tech","hint_year":2006,"hint_status":"debunked"},
    {"name":"Tartaria / Mud Flood","hint_genre":"alt-history","hint_year":2016,"hint_status":"debunked"},
    {"name":"Phantom Time Hypothesis","hint_genre":"alt-history","hint_year":1991,"hint_status":"debunked"},
    {"name":"New Chronology (Fomenko)","hint_genre":"alt-history","hint_year":1980,"hint_status":"debunked"},
    {"name":"Pre-Columbian Transoceanic Contact","hint_genre":"alt-history","hint_year":1960,"hint_status":"contested"},
    {"name":"Nazi Gold / Hidden Treasure","hint_genre":"alt-history","hint_year":1945,"hint_status":"plausible"},
    {"name":"Nazi UFOs / Antarctic Base","hint_genre":"alt-history","hint_year":1978,"hint_status":"debunked"},
    {"name":"Birds Aren't Real","hint_genre":"science-tech","hint_year":2017,"hint_status":"debunked"},
    {"name":"Bielefeld Conspiracy","hint_genre":"alt-history","hint_year":1994,"hint_status":"debunked"},
    {"name":"Loch Ness Monster Cover-up","hint_genre":"science-tech","hint_year":1933,"hint_status":"fringe"},
    {"name":"Bigfoot Cover-up","hint_genre":"science-tech","hint_year":1958,"hint_status":"fringe"},
    {"name":"Melania Trump Body Double","hint_genre":"deaths","hint_year":2017,"hint_status":"fringe"},
    {"name":"Dave Chappelle Clone","hint_genre":"media-surveillance","hint_year":2006,"hint_status":"fringe"},
    {"name":"Stanley Kubrick Filmed the Moon Landing","hint_genre":"science-tech","hint_year":2002,"hint_status":"debunked"},
    {"name":"JonBenet Ramsey Cover-up","hint_genre":"deaths","hint_year":1996,"hint_status":"contested"},
    {"name":"Madeleine McCann Theories","hint_genre":"deaths","hint_year":2007,"hint_status":"contested"},
    {"name":"Harold Holt Chinese Submarine","hint_genre":"deaths","hint_year":1983,"hint_status":"debunked"},
    {"name":"Gaylor (Taylor Swift)","hint_genre":"media-surveillance","hint_year":2019,"hint_status":"fringe"},
    {"name":"Larries (One Direction)","hint_genre":"media-surveillance","hint_year":2011,"hint_status":"fringe"},
    {"name":"NBA Frozen Envelope Draft","hint_genre":"government","hint_year":1985,"hint_status":"contested"},
    {"name":"Ali vs Liston Phantom Punch","hint_genre":"government","hint_year":1965,"hint_status":"contested"},
    {"name":"1998 World Cup Ronaldo Fix","hint_genre":"government","hint_year":1998,"hint_status":"fringe"},
    {"name":"Shergar Racehorse Theft","hint_genre":"government","hint_year":1983,"hint_status":"contested"},
    {"name":"New Coke Deliberate Failure","hint_genre":"finance","hint_year":1985,"hint_status":"debunked"},
    {"name":"Deepwater Horizon Sabotage","hint_genre":"government","hint_year":2010,"hint_status":"debunked"},
    {"name":"Tsunami Bomb / 2004 Indian Ocean","hint_genre":"science-tech","hint_year":2005,"hint_status":"debunked"},
    {"name":"Haiti Earthquake Weapon","hint_genre":"science-tech","hint_year":2010,"hint_status":"debunked"},
    {"name":"Project Cumulus Lynmouth Flood","hint_genre":"science-tech","hint_year":1952,"hint_status":"contested"},
    {"name":"Weather Modification Cloud Seeding","hint_genre":"science-tech","hint_year":1947,"hint_status":"plausible"},
    {"name":"Anti-Fluoridation Communist Plot","hint_genre":"health","hint_year":1955,"hint_status":"debunked"},
    {"name":"Titanic / Olympic Switch","hint_genre":"alt-history","hint_year":1995,"hint_status":"debunked"},
    {"name":"Denver Airport Blue Mustang (Blucifer)","hint_genre":"new-world-order","hint_year":2008,"hint_status":"fringe"},
    {"name":"Vatican / Third Secret of Fatima","hint_genre":"religion-occult","hint_year":1960,"hint_status":"contested"},
    {"name":"Holy Blood, Holy Grail / Jesus Bloodline","hint_genre":"religion-occult","hint_year":1982,"hint_status":"debunked"},
    {"name":"Shakespeare Authorship","hint_genre":"alt-history","hint_year":1857,"hint_status":"contested"},
    {"name":"Global Warming Pause / Climategate","hint_genre":"science-tech","hint_year":2009,"hint_status":"debunked"},
    {"name":"Fake Snow (Government Snow)","hint_genre":"science-tech","hint_year":2021,"hint_status":"debunked"},
    {"name":"Flight MH370 Diego Garcia","hint_genre":"government","hint_year":2014,"hint_status":"debunked"},
    {"name":"Amelia Earhart Japanese Capture","hint_genre":"deaths","hint_year":1943,"hint_status":"contested"},
    {"name":"Roswell Alien Autopsy Film","hint_genre":"extraterrestrial","hint_year":1995,"hint_status":"debunked"},
    {"name":"Men in Black","hint_genre":"extraterrestrial","hint_year":1953,"hint_status":"fringe"},
    {"name":"Disclosure Project","hint_genre":"extraterrestrial","hint_year":2001,"hint_status":"contested"},
    {"name":"Pentagon UAP Disclosure","hint_genre":"extraterrestrial","hint_year":2017,"hint_status":"plausible"},
    {"name":"Wow! Signal Alien Contact","hint_genre":"extraterrestrial","hint_year":1977,"hint_status":"contested"},
    {"name":"Moon Is Hollow / Artificial","hint_genre":"extraterrestrial","hint_year":1970,"hint_status":"fringe"},
    {"name":"Antarctica Hidden Truth","hint_genre":"alt-history","hint_year":2016,"hint_status":"fringe"},
    {"name":"Flat Earth Ice Wall / Antarctica Guard","hint_genre":"science-tech","hint_year":2015,"hint_status":"debunked"}
  ]
}
